{
  "format_version": "1.21.50",
  "minecraft:recipe_shaped": {
    "description": {
      "identifier": "ghozix_idlegen:coal_generator_recipe"
    },
    "tags": ["crafting_table"],
    "pattern": ["GFG", "FBF", "GFG"],
    "key": {
      "G": { "item": "minecraft:glass" },
      "F": { "item": "minecraft:furnace" },
      "B": { "item": "minecraft:coal_block" }
    },
    "unlock": [
      {
        "item": "minecraft:coal"
      }
    ],
    "result": {
      "item": "ghozix_idlegen:coal_generator",
      "count": 1
    }
  }
}
